ecal_api/__init__.py
ecal_api/account_api.py
ecal_api/calendar_api.py
ecal_api/event_api.py
ecal_api/subscriber_api.py
ecal_api/utils.py
ecal_api-1.4.1.dist-info/LICENCE
ecal_api-1.4.1.dist-info/METADATA
ecal_api-1.4.1.dist-info/WHEEL
ecal_api-1.4.1.dist-info/top_level.txt
ecal_api-1.4.1.dist-info/RECORD
