Metadata-Version: 2.1
Name: ecal-api
Version: 1.4.1
Summary: A Python library for interacting with the ECAL API
Author: NathanSbds
Author-email: nathan.sbds@icloud.com
License-File: LICENCE
Requires-Dist: requests
